{"configVersion":1,"timestamp":1751881695132,"index":"/index.html","assetGroups":[{"name":"app","installMode":"prefetch","updateMode":"prefetch","cacheQueryOptions":{"ignoreVary":true},"urls":["/chunk-26PW3M2Z.js","/chunk-2YXAMA7R.js","/chunk-352URA43.js","/chunk-3GXG4AQJ.js","/chunk-4AGVF2F7.js","/chunk-5BL5ZF4M.js","/chunk-5BN5PN2Q.js","/chunk-5MZAELST.js","/chunk-6FLMXVFD.js","/chunk-6NTZFB3I.js","/chunk-6TSMBYSC.js","/chunk-APVWBNLP.js","/chunk-B4JGQHR5.js","/chunk-B6KQYFDQ.js","/chunk-D75AIWI5.js","/chunk-DAHELYEP.js","/chunk-DRT7ZDXW.js","/chunk-DXDQQFS5.js","/chunk-FIBLSUHV.js","/chunk-G6DHYIGB.js","/chunk-HSBRWJAU.js","/chunk-JJLWTDCJ.js","/chunk-JTA3MAX4.js","/chunk-K3XCWOZ7.js","/chunk-KBK7RMLB.js","/chunk-NTKJDTVX.js","/chunk-NZZI52FP.js","/chunk-OZKMM2UK.js","/chunk-PECOJE4E.js","/chunk-PGHX4PKI.js","/chunk-PNR7Z2VE.js","/chunk-PP545VVJ.js","/chunk-QJNRM3DI.js","/chunk-QJRUSWPR.js","/chunk-QPKJLFQT.js","/chunk-QWAMJNYY.js","/chunk-R4G4X3NR.js","/chunk-SAWFLHZQ.js","/chunk-TA7EFEO7.js","/chunk-TQDCXJM3.js","/chunk-TX3LXRZO.js","/chunk-WGDJRT2X.js","/chunk-X56CJT5Y.js","/chunk-XC3VZOJM.js","/chunk-XCBMKKKR.js","/chunk-XNQE5CNG.js","/chunk-Z4C2Y2ZE.js","/index.html","/main-7GQHB4Y6.js","/ngsw-worker.js","/polyfills-KAH7MPAQ.js","/safety-worker.js","/scripts-RST73XXA.js","/styles-HEMZV2YQ.css","/worker-basic.min.js"],"patterns":["https:\\/\\/gw\\.alipayobjects\\.com\\/.*","https:\\/\\/img\\.alicdn\\.com\\/.*","https:\\/\\/dummyimage\\.com\\/.*"]},{"name":"assets","installMode":"lazy","updateMode":"prefetch","cacheQueryOptions":{"ignoreVary":true},"urls":["/assets/LOGO.ai","/assets/demo.docx","/assets/demo.pdf","/assets/demo.pptx","/assets/demo.xlsx","/assets/demo.zip","/assets/donate.png","/assets/highlight.pack.js","/assets/icons/icon-128x128.png","/assets/icons/icon-144x144.png","/assets/icons/icon-152x152.png","/assets/icons/icon-192x192.png","/assets/icons/icon-384x384.png","/assets/icons/icon-512x512.png","/assets/icons/icon-72x72.png","/assets/icons/icon-96x96.png","/assets/img/404.jpg","/assets/img/avatar.jpg","/assets/img/form-input.png","/assets/img/logo-color.png","/assets/img/logo-color.svg","/assets/img/logo-full.svg","/assets/img/logo.png","/assets/img/logo.svg","/assets/img/ng-alain.svg","/assets/img/plnkr.png","/assets/img/zorro.svg","/assets/jszip/jszip.min.js","/assets/logo-color.svg","/assets/logo-full.svg","/assets/logo.svg","/assets/plyr/plyr.css","/assets/plyr/plyr.min.js","/assets/plyr/plyr.svg","/assets/pro.png","/assets/qq-group.png","/assets/qrious/qrious.min.js","/assets/schema/basic.json","/assets/schema/conditional.json","/assets/schema/fixed.json","/assets/schema/onboarding.json","/assets/schema/sort.json","/assets/schema/validation.json","/assets/screenshot/architecture.png","/assets/screenshot/basic.png","/assets/screenshot/bundle-size.png","/assets/screenshot/data.webp","/assets/screenshot/desktop.png","/assets/screenshot/ipad.png","/assets/screenshot/iphone.png","/assets/screenshot/ms.png","/assets/screenshot/pro.png","/assets/screenshot/start.png","/assets/screenshot/yun.png","/assets/style.compact.css","/assets/style.dark.css","/assets/xlsx/cpexcel.js","/assets/xlsx/xlsx.full.min.js","/assets/yarn.lock.txt"],"patterns":[]}],"dataGroups":[],"hashTable":{"/assets/LOGO.ai":"f0eb50ff534d6596d2e66439066909d965fd74f2","/assets/demo.docx":"e6cf4a7b4a490811ed5bec39e8cf203824e8703f","/assets/demo.pdf":"05248c1d4a636ee577f515809534ca1c85cd45c2","/assets/demo.pptx":"09fcb13206d59676838c2682a2a9b62f0a11863b","/assets/demo.xlsx":"fbfaf8aa861857adadaf89b28fe31ad3100395ea","/assets/demo.zip":"99584e56a5910ccb3d58d6dbbbf4c341747b9d57","/assets/donate.png":"e00d7905db3e9e5a8365072da22bf4816224a79c","/assets/highlight.pack.js":"d43298ac40a94f15d24baaa1f9d4087a7c1a2146","/assets/icons/icon-128x128.png":"a64acae4187c0ac026f569727d427e510e57bd3c","/assets/icons/icon-144x144.png":"3777651bff501b02af74e14a4a7d97330ed06b51","/assets/icons/icon-152x152.png":"1ce29288030cd2787bca6f9e20a9d9ea543c807d","/assets/icons/icon-192x192.png":"027f8042ef3f22333b7f57463f764c14fb10ddda","/assets/icons/icon-384x384.png":"8c398368508ae5b7e7b0f0b500493cb75e5d1ada","/assets/icons/icon-512x512.png":"a8d39cf76ddcb33fa87d534476b2cdefa733d5fe","/assets/icons/icon-72x72.png":"3771059af6090c411bae02002f2e1d7877c368e9","/assets/icons/icon-96x96.png":"400b8ad0e5b8bf5ac0740b3f480e713b2a3fc0e5","/assets/img/404.jpg":"9604038f6b13cb304a14a13b2fa76d43444b4414","/assets/img/avatar.jpg":"1258f9ead6901ff45abd313a1b4f265749749b58","/assets/img/form-input.png":"75c924b9bd023a5e27e9745936a27caaf20a1537","/assets/img/logo-color.png":"8defcb0c2b47a66d7c1b57f78525e488adc62642","/assets/img/logo-color.svg":"587f7e7d6cacc6eb7222b99c08d3df8abc8edd4e","/assets/img/logo-full.svg":"fed68d999561a3180b925071180d3d4cfd2b8440","/assets/img/logo.png":"7dcbf051ab322ef1bd076940e981bf9abdd5ae78","/assets/img/logo.svg":"a2334b77c19d8dc880bbbd82e9939a0aa8d59573","/assets/img/ng-alain.svg":"fb55683a364df5de725cb98a7c51b2eb21ca4de6","/assets/img/plnkr.png":"dc4da4819d5a9b4ff44f1457f96808a761ab9143","/assets/img/zorro.svg":"82d83c92dff3114bd45e985e3c8e402f37a4beb9","/assets/jszip/jszip.min.js":"c96375d50e72b199aa54de7b9ad908fd5a2dc7bc","/assets/logo-color.svg":"587f7e7d6cacc6eb7222b99c08d3df8abc8edd4e","/assets/logo-full.svg":"fed68d999561a3180b925071180d3d4cfd2b8440","/assets/logo.svg":"a2334b77c19d8dc880bbbd82e9939a0aa8d59573","/assets/plyr/plyr.css":"3e9561fb7a2a70b93bb1014f5d958b123fe61764","/assets/plyr/plyr.min.js":"9b165c0e728a0ac4e2cddc944c9a2c5819ca7342","/assets/plyr/plyr.svg":"bc98e4a347921594352fbae53aaad185c0c7f6b5","/assets/pro.png":"0e8e2bd64766aab6e12f44607ad7e92aec241468","/assets/qq-group.png":"1effddfab735644966df1759c2768f282a3e650e","/assets/qrious/qrious.min.js":"a9271e81e2ac6a692b1c133811afa33f0f3d7dc5","/assets/schema/basic.json":"d3b26817208571cfed1a5dd667875c358b1d7e1f","/assets/schema/conditional.json":"204f15af35cc98d5d692c7265d84d2645a6394f0","/assets/schema/fixed.json":"f4d6c6c66503ec0c817ab89e8538c2be028c7cff","/assets/schema/onboarding.json":"20c6f311cc99ccbf7180afb906e9abf74473786b","/assets/schema/sort.json":"850f554e1a7db144e9ad305b6a3ad79bfb58ca28","/assets/schema/validation.json":"0a5971cb42a49672e0005b88036ef47bc8cebe94","/assets/screenshot/architecture.png":"9e19b12a25deab3280ebf5795597a90af29c4c38","/assets/screenshot/basic.png":"42a70c07d9f35413991972634011459fdb010022","/assets/screenshot/bundle-size.png":"f67a8b0678161abce9afcb694db3c02d3b4b5f73","/assets/screenshot/data.webp":"286aec35bb8a1bc624d8fcfedf1a03bc08098438","/assets/screenshot/desktop.png":"42a70c07d9f35413991972634011459fdb010022","/assets/screenshot/ipad.png":"0fc5d85a81da2057ec68fc9094c0cb5c862bf309","/assets/screenshot/iphone.png":"6b7d70c66cd422ad5aee06d91ddb39c7fd0558bb","/assets/screenshot/ms.png":"26b0065c7c5d4f9f9c6b0efa4915eb6576caee75","/assets/screenshot/pro.png":"37bd67671530613e955593eb3fc818e27d18dcb6","/assets/screenshot/start.png":"8af50c7dbc9bab333f7e88b67debb6657bc61ed9","/assets/screenshot/yun.png":"b0e3dec2af4dfae8f25e5d90f19cd3c60107e89f","/assets/style.compact.css":"0cc7fc6e5259630d3d4193a38d74f81395a5c887","/assets/style.dark.css":"106cba01c5c346f684fda572456b0e05b4171b42","/assets/xlsx/cpexcel.js":"9191595b39ba1918d32fb250d3ff21d07f99fc19","/assets/xlsx/xlsx.full.min.js":"7f749f81a45a53229136c6c1f1d50dcb16ddc233","/assets/yarn.lock.txt":"34f9d753b44091f02c82cb6c9a74be18bb397293","/chunk-26PW3M2Z.js":"fa6c8718dc4be9021d9ea115f03cda7fca5a58a7","/chunk-2YXAMA7R.js":"5f4c2e6f12d9920e048b6e69267a89c1d24a6dd4","/chunk-352URA43.js":"c4ebf443eb9da4d2e979ddf4387780b99bc35b9f","/chunk-3GXG4AQJ.js":"f6512252b3fd89dd387c87b2b4b97eabe08853fe","/chunk-4AGVF2F7.js":"70bd76757f8794f791f2e48a44aa23bd564bf7a5","/chunk-5BL5ZF4M.js":"b11b59fad729f6b9e81643e01eecf22815c2dc52","/chunk-5BN5PN2Q.js":"319260d4208089d0a8979f3034463ed185b89c05","/chunk-5MZAELST.js":"8bda2538888c4cef434b4d41da150b70f9d6d97a","/chunk-6FLMXVFD.js":"383632f3965426e3018ff29fd7f305d957e70d16","/chunk-6NTZFB3I.js":"e21062eeb5a1d047322176f30ad44cf8b5032ef5","/chunk-6TSMBYSC.js":"9e54d12f25f4e79e1fb5348867cdb0854f6012dc","/chunk-APVWBNLP.js":"b4b5c387d363d8df3499f3b03d26a1d95a971ad9","/chunk-B4JGQHR5.js":"65516e763078c570c3d5743e01a8219e542e871c","/chunk-B6KQYFDQ.js":"ccdd93873386286a1495355902aa4f428d596ea7","/chunk-D75AIWI5.js":"fc9c9e4c70ed3f9fd3053121c19d4db625451e69","/chunk-DAHELYEP.js":"98cbd275d0f4feef2cd6bfeb782657a36dc6db09","/chunk-DRT7ZDXW.js":"ba393a8e6506193cab4e78c535a4fe2c5ad5ebdc","/chunk-DXDQQFS5.js":"e726631eae3295b8ae005eb4da99762a9e3dfd16","/chunk-FIBLSUHV.js":"76dbcb8e8346253b9de7c8e97b7ef12e8a9a0da4","/chunk-G6DHYIGB.js":"865d8e7f62454084f1882e5a62477814ed5c6cf7","/chunk-HSBRWJAU.js":"4870af5b08b9cc43ac5aaf0d8edbc216058deec5","/chunk-JJLWTDCJ.js":"2d72d3026b013f989f40e797b7edfb9fd7060a10","/chunk-JTA3MAX4.js":"1c187a92828f0cdf9f7df57b793bb46cb69cf8f4","/chunk-K3XCWOZ7.js":"91ce461483fead81d89a82741ab0375e3045305b","/chunk-KBK7RMLB.js":"0b4c647a191674a8e25abfca55e2ee9a20f7c623","/chunk-NTKJDTVX.js":"0379b91a0be4d2ebc0748938db5edd2326c61955","/chunk-NZZI52FP.js":"2ad0ae71c0bbcef2375c7698cde1a03077a63526","/chunk-OZKMM2UK.js":"58efc533bc1f5ca8b303d483775940eb1d3e0c3c","/chunk-PECOJE4E.js":"93b42ca4a1a9fd5b49ca6566e9ea88b89955f94c","/chunk-PGHX4PKI.js":"6c28cec855f0663159443f3e15ec4c5da0193788","/chunk-PNR7Z2VE.js":"dafc7d06aa56e24d159a1f34794f87b2de3ed40c","/chunk-PP545VVJ.js":"ff25c6ef1fdc120f12f85a8ad280dc24df5bd98f","/chunk-QJNRM3DI.js":"55c36c887caeaa503ab998592fef6a1ef79657a2","/chunk-QJRUSWPR.js":"4b862aa0d8c49dc9fd391798ddc9a5893452f1f5","/chunk-QPKJLFQT.js":"ae029990f65667c8397ef7f2fa320dcedfdf24ac","/chunk-QWAMJNYY.js":"cbecaa52867ddf5ff61614fb2d47c0590f8dba3c","/chunk-R4G4X3NR.js":"097b2b422a1df5c39fe41904496e71feeb61aebd","/chunk-SAWFLHZQ.js":"a36ba002f70144d1f7f39d229579f5267dc33591","/chunk-TA7EFEO7.js":"215d53116cc7a4dca2f9da16c065aea5f5b2922c","/chunk-TQDCXJM3.js":"c08bb382587133c986efe7fa2a48743058bcee67","/chunk-TX3LXRZO.js":"1ece743cf35a423b82ab25d05be605138df5ee82","/chunk-WGDJRT2X.js":"93d8e44d26f69ff94c5f4e8364bdd42c3a62e969","/chunk-X56CJT5Y.js":"d2a1d2b5b7be9728e5659a47afe506dc6f11ec04","/chunk-XC3VZOJM.js":"3f1342fcceeb1255bcd9e6c9b73f2debcda8bd0d","/chunk-XCBMKKKR.js":"4ebd091d9d6e3418dc3268e69d7c8b53dfa80b2e","/chunk-XNQE5CNG.js":"8799adf2932046344605546945a5e6dca33a0c6c","/chunk-Z4C2Y2ZE.js":"a9ce68d054c57ad242e4de5bd1ae9265e39e9cee","/index.html":"1c6774fce709afe9bd3a7d5cc209cc1d5f629158","/main-7GQHB4Y6.js":"8fc1c0d04aeede69b265de532bbc7bb56500c044","/ngsw-worker.js":"c92790d3b1b6c847f2c974ad4cc96598451eb579","/polyfills-KAH7MPAQ.js":"8ad38593acf4c035df3067c30e78ac1441ecece1","/safety-worker.js":"3b3c24f5fca13ee61325298c2009282aeef273c7","/scripts-RST73XXA.js":"1a891857a05b3d7ca4308fa80e2c168732f39d72","/styles-HEMZV2YQ.css":"952dcb52fbec32ad6f75c4ad95993f121e2bd910","/worker-basic.min.js":"3b3c24f5fca13ee61325298c2009282aeef273c7"},"navigationUrls":[{"positive":true,"regex":"^\\/.*$"},{"positive":false,"regex":"^\\/(?:.+\\/)?[^/]*\\.[^/]*$"},{"positive":false,"regex":"^\\/(?:.+\\/)?[^/]*__[^/]*$"},{"positive":false,"regex":"^\\/(?:.+\\/)?[^/]*__[^/]*\\/.*$"},{"positive":false,"regex":"^\\/(?:.+\\/)?stackblitz$"},{"positive":false,"regex":"^\\/version\\/.*$"},{"positive":false,"regex":"^\\/issue-helper\\/.*$"},{"positive":false,"regex":"^\\/docs\\/(?:.+\\/)?[^/]*$"},{"positive":false,"regex":"^\\/docs\\/[^/][^/]*$"},{"positive":false,"regex":"^\\/components\\/(?:.+\\/)?[^/]*$"},{"positive":false,"regex":"^\\/components\\/[^/][^/]*$"},{"positive":false,"regex":"^\\/cli\\/(?:.+\\/)?[^/]*$"},{"positive":false,"regex":"^\\/cli\\/[^/][^/]*$"},{"positive":false,"regex":"^\\/theme\\/(?:.+\\/)?[^/]*$"},{"positive":false,"regex":"^\\/theme\\/[^/][^/]*$"},{"positive":false,"regex":"^\\/auth\\/(?:.+\\/)?[^/]*$"},{"positive":false,"regex":"^\\/auth\\/[^/][^/]*$"},{"positive":false,"regex":"^\\/acl\\/(?:.+\\/)?[^/]*$"},{"positive":false,"regex":"^\\/acl\\/[^/][^/]*$"},{"positive":false,"regex":"^\\/form\\/(?:.+\\/)?[^/]*$"},{"positive":false,"regex":"^\\/form\\/[^/][^/]*$"},{"positive":false,"regex":"^\\/cache\\/(?:.+\\/)?[^/]*$"},{"positive":false,"regex":"^\\/cache\\/[^/][^/]*$"},{"positive":false,"regex":"^\\/chart\\/(?:.+\\/)?[^/]*$"},{"positive":false,"regex":"^\\/chart\\/[^/][^/]*$"},{"positive":false,"regex":"^\\/mock\\/(?:.+\\/)?[^/]*$"},{"positive":false,"regex":"^\\/mock\\/[^/][^/]*$"},{"positive":false,"regex":"^\\/util\\/(?:.+\\/)?[^/]*$"},{"positive":false,"regex":"^\\/util\\/[^/][^/]*$"}],"navigationRequestStrategy":"performance","local":"en"}
